cite_master/Papers.txt
cite_master/__init__.py
cite_master/__main__.py
cite_master/extract_doi.py
cite_master/fetch_bibtex.py
cite_master/formatter.py
cite_master-0.1.1.dist-info/LICENSE
cite_master-0.1.1.dist-info/METADATA
cite_master-0.1.1.dist-info/WHEEL
cite_master-0.1.1.dist-info/entry_points.txt
cite_master-0.1.1.dist-info/top_level.txt
cite_master-0.1.1.dist-info/RECORD
