Metadata-Version: 2.1
Name: cite_master
Version: 0.1.1
Summary: A tool to automatically generate formatted citations from paper titles
Home-page: https://github.com/mehmoodulhaq570/CiteMaster
Author: Mehmood Ul Haq
Author-email: mehmooulhaq1040@gmail.com
License: MIT
Project-URL: Documentation, https://github.com/mehmoodulhaq570/CiteMaster#readme
Project-URL: Source, https://github.com/mehmoodulhaq570/CiteMaster
Project-URL: Bug Tracker, https://github.com/mehmoodulhaq570/CiteMaster/issues
Classifier: Programming Language :: Python :: 3
Classifier: License :: OSI Approved :: MIT License
Classifier: Operating System :: OS Independent
Requires-Python: >=3.7
License-File: LICENSE
Requires-Dist: requests>=2.25.1
Requires-Dist: tqdm>=4.59.0
Requires-Dist: beautifulsoup4>=4.9.3
Requires-Dist: pandas>=1.2.4
